smlfm/__init__.py
smlfm/config.py
smlfm/fiji_app.py
smlfm/fitting.py
smlfm/fourier_microscope.py
smlfm/localisation_file.py
smlfm/localisations.py
smlfm/micro_lens_array.py
smlfm/output_files.py
smlfm/data/default-config.json
smlfm/data/tdy-watermark.png
smlfm/graphs/__init__.py
smlfm/graphs/add_watermark.py
smlfm/graphs/draw_3d_locs.py
smlfm/graphs/draw_histogram.py
smlfm/graphs/draw_locs.py
smlfm/graphs/draw_locs_csv.py
smlfm/graphs/draw_locs_normalised.py
smlfm/graphs/draw_mla.py
smlfm/graphs/draw_occurrences.py
smlfm/graphs/reconstruct_results.py
smlfm_cli/__init__.py
smlfm_cli/__main__.py
smlfm_cli/app.py
smlfm_gui/__init__.py
smlfm_gui/__main__.py
smlfm_gui/app.py
smlfm_gui/app_model.py
smlfm_gui/assets.py
smlfm_gui/cfg_dialog.py
smlfm_gui/config_cfg_dialog.py
smlfm_gui/config_frame.py
smlfm_gui/consts.py
smlfm_gui/correct_cfg_dialog.py
smlfm_gui/correct_frame.py
smlfm_gui/csv_frame.py
smlfm_gui/figure_window.py
smlfm_gui/filter_cfg_dialog.py
smlfm_gui/filter_frame.py
smlfm_gui/fit_cfg_dialog.py
smlfm_gui/fit_frame.py
smlfm_gui/optics_cfg_dialog.py
smlfm_gui/optics_frame.py
smlfm_gui/data/LICENSE-icons
smlfm_gui/data/apps_black_18dp.svg
smlfm_gui/data/bar_chart_black_18dp.svg
smlfm_gui/data/biotech_black_18dp.svg
smlfm_gui/data/cancel_black_18dp.svg
smlfm_gui/data/circle-small.svg
smlfm_gui/data/collections_black_18dp.svg
smlfm_gui/data/construction_black_18dp.svg
smlfm_gui/data/done_black_18dp.svg
smlfm_gui/data/dots-grid.svg
smlfm_gui/data/dots-hexagon.svg
smlfm_gui/data/dots-triangle.svg
smlfm_gui/data/filter_alt_black_18dp.svg
smlfm_gui/data/folder_open_black_18dp.svg
smlfm_gui/data/mediation_black_18dp.svg
smlfm_gui/data/numeric-1.svg
smlfm_gui/data/numeric-2.svg
smlfm_gui/data/numeric-3.svg
smlfm_gui/data/numeric-4.svg
smlfm_gui/data/numeric-5.svg
smlfm_gui/data/numeric-6.svg
smlfm_gui/data/panorama_horizontal_select_black_18dp.svg
smlfm_gui/data/play_arrow_black_18dp.svg
smlfm_gui/data/rotate-orbit.svg
smlfm_gui/data/save_as_black_18dp.svg
PySMLFM-1.0.0.dist-info/LICENSE
PySMLFM-1.0.0.dist-info/METADATA
PySMLFM-1.0.0.dist-info/WHEEL
PySMLFM-1.0.0.dist-info/entry_points.txt
PySMLFM-1.0.0.dist-info/top_level.txt
PySMLFM-1.0.0.dist-info/RECORD
