Metadata-Version: 2.1
Name: PySMLFM
Version: 1.0.0
Summary: Single Molecule Light Field Microscopy Reconstruction
Home-page: https://github.com/Photometrics/PySMLFM
Author: Teledyne Photometrics
Author-email: Tomáš Hanák <tomas.hanak@teledyne.com>
License: GPL-3.0-or-later
Project-URL: homepage, https://github.com/Photometrics/PySMLFM
Project-URL: source, https://github.com/Photometrics/PySMLFM
Project-URL: download, https://pypi.org/project/PySMLFM/
Project-URL: tracker, https://github.com/Photometrics/PySMLFM/issues
Keywords: microscopy,lightfield
Classifier: Development Status :: 5 - Production/Stable
Classifier: Intended Audience :: Science/Research
Classifier: License :: OSI Approved :: GNU General Public License v3 or later (GPLv3+)
Classifier: Operating System :: MacOS :: MacOS X
Classifier: Operating System :: Microsoft :: Windows
Classifier: Operating System :: POSIX :: Linux
Classifier: Programming Language :: Python :: 3 :: Only
Classifier: Programming Language :: Python :: 3.8
Classifier: Programming Language :: Python :: 3.9
Classifier: Programming Language :: Python :: 3.10
Classifier: Programming Language :: Python :: 3.11
Classifier: Programming Language :: Python :: 3.12
Classifier: Topic :: Scientific/Engineering :: Image Processing
Classifier: Topic :: Scientific/Engineering :: Visualization
Classifier: Topic :: Software Development :: Libraries :: Python Modules
Requires-Python: >=3.8
License-File: LICENSE
Requires-Dist: numpy ~=1.20
Requires-Dist: scikit-learn ~=1.3
Requires-Dist: matplotlib ~=3.6
Requires-Dist: cairosvg ~=2.0
Provides-Extra: dev
Requires-Dist: pytest >=6.0 ; extra == 'dev'
Requires-Dist: validate-pyproject[all] ; extra == 'dev'
Requires-Dist: Flake8-pyproject ; extra == 'dev'
Requires-Dist: flake8-typing-imports ; extra == 'dev'
Requires-Dist: pylint ; extra == 'dev'
Provides-Extra: fiji
Requires-Dist: pyimagej ~=1.4 ; extra == 'fiji'
